{
  "users": [
    {
      "id": 4658805,
      "firstName": "Jamie",
      "lastName": "Fay",
      "email": "Mossie_Johnston21@gmail.com"
    },
    {
      "id": 12923709,
      "firstName": "Griffin",
      "lastName": "Shanahan",
      "email": "Judah64@hotmail.com"
    },
    {
      "id": 94163512,
      "firstName": "Susanna",
      "lastName": "Orn",
      "email": "Aubrey41@hotmail.com"
    },
    {
      "id": 81540824,
      "firstName": "Peyton",
      "lastName": "Rosenbaum",
      "email": "Pete_Hackett41@gmail.com"
    },
    {
      "id": 76249130,
      "firstName": "Justen",
      "lastName": "Hagenes",
      "email": "Diamond89@gmail.com"
    },
    {
      "id": 72169429,
      "firstName": "Princess",
      "lastName": "Mueller",
      "email": "Ibrahim42@hotmail.com"
    },
    {
      "id": 78815036,
      "firstName": "Quinn",
      "lastName": "Wolff",
      "email": "Stella.Kovacek@gmail.com"
    },
    {
      "id": 38358266,
      "firstName": "Ezequiel",
      "lastName": "Denesik",
      "email": "Billy_Jerde32@hotmail.com"
    }
  ]
}